[{"title":"1817年:纽约证券交易所成立。","year":1817},{"title":"1844年:瑞典和挪威国王卡尔十四世·约翰去世，其子奥斯卡一世继承王位。","year":1844},{"title":"1909年:美国芝加哥妇女大游行。","year":1909},{"title":"1917年:俄国彼得格勒的工人举行罢工和游行，二月革命爆发。","year":1917},{"title":"1918年:安福俱乐部成立，安福系开始控制中华民国政权。","year":1918},{"title":"1939年:抗战:日军占领南昌。","year":1939},{"title":"1942年:太平洋战争:爪哇岛荷兰军队向日军投降，同日日军占领缅甸首都仰光。","year":1942},{"title":"1947年:蒋介石在陈仪的暗中要求下，增派陆军整编第21师与宪兵第4团等军队共一万三千人自中国大陆抵达台湾展开二二八事件的镇压屠杀与清乡。","year":1947},{"title":"1950年:苏联宣称自己拥有了核弹。","year":1950},{"title":"1954年:《美日共同防御协定》签署。","year":1954},{"title":"1965年:越南战争:美国海军陆战队登陆南越岘港，标志着美军开始直接参战。","year":1965},{"title":"1966年:中国河北邢台发生地震。","year":1966},{"title":"1974年:法国巴黎夏尔·戴高乐国际机场正式启用。","year":1974},{"title":"1976年:中国吉林省降落罕见陨石雨。","year":1976},{"title":"1983年:美国总统里根在佛罗里达州奥兰多的一场演讲中称苏联为邪恶帝国。","year":1983},{"title":"1985年:非洲前线国家首脑会议在卢萨卡举行。","year":1985},{"title":"1996年:中国于台湾沿海进行第一波的导弹演习。","year":1996},{"title":"2000年:日本东京都发生营团地下铁日比谷线事故。","year":2000},{"title":"2008年:2008年马来西亚第十二届全国大选，执政联盟国阵再度执政马来西亚下议院，但是却在本届大选中失去五个州政权和三分之二席位的优势。","year":2008},{"title":"2013年:朝鲜祖国和平统一委员会宣布将全面废除朝韩之间签订的互不侵犯协议，切断朝韩热线电话等板门店联络渠道。","year":2013},{"title":"2014年:马来西亚航空370号班机在执行由吉隆坡国际机场飞往北京首都国际机场航线时于马来西亚当地时间凌晨1时21分在马来西亚与越南的航空管制区内失去与塔台的联系，之后该机折返回马来西亚，并在马来西亚霹雳岛上空失去卫星联络讯号，至今下落不明。","year":2014}]