[{"title":"1803年:清朝封阮福映为安南国王。","year":1803},{"title":"1814年:好望角省成为英国殖民地。","year":1814},{"title":"1889年:美国人威廉·格雷获得投币式电话专利。","year":1889},{"title":"1891年:中华民国前任代总统李宗仁出生。","year":1891},{"title":"1905年:挪威成为独立国家。","year":1905},{"title":"1912年:法国医生加斯顿·奥丁发现癌细胞。","year":1912},{"title":"1920年:波苏战争:华沙战役打响。","year":1920},{"title":"1937年:日军在上海以租界和军舰为基地，向中国守军发起攻击，淞沪会战爆发。","year":1937},{"title":"1940年:第二次世界大战:不列颠空战爆发。","year":1940},{"title":"1958年:大跃进:中国湖北麻城早稻产量放卫星，根据《人民日报》报道，麻溪河乡建国第一农业社早稻田创造了平均亩产干谷三万六千九百五十六斤的惊人纪录。","year":1958},{"title":"1960年:中非共和国宣布脱离法国独立。","year":1960},{"title":"1961年:民主德国开始围绕西柏林建造柏林墙，封锁了东柏林和西柏林之间的交通往来。","year":1961},{"title":"1968年:希腊政治家亚历山德罗斯·帕纳古利斯尝试暗杀希腊军政府独裁者乔治斯·帕帕佐普洛斯。","year":1968},{"title":"1969年:苏联与中国在新疆铁列克提发生军事冲突。","year":1969},{"title":"1985年:中华人民共和国国务院批准实施星火计划。","year":1985},{"title":"2001年:日本内阁总理大臣小泉纯一郎参拜供奉第二次世界大战甲级战犯的靖国神社，引起中国、韩国、朝鲜等国家的强烈谴责。","year":2001},{"title":"2004年:第28届奥林匹克运动会在希腊雅典正式开幕。","year":2004},{"title":"2005年:香港观塘创纪之城1期的外墙及对开巴士站凌晨疑遭雷电击中，巴士站的广告牌毁烂，大厦数块玻璃及外墙云石碎裂。","year":2005},{"title":"2007年:中国湖南省凤凰县刚刚竣工的沱江大桥倒塌。","year":2007},{"title":"2016年:科学家发现栖息在格陵兰和冰岛周围北大西洋海域的小头睡鲨是世界上最长寿的脊椎动物。","year":2016},{"title":"2014年:一架私人飞机在巴西圣保罗州桑托斯市附近的住宅区坠落，造成多人伤亡，即将于10月角逐巴西总统大选的爱德华多·坎波斯于这场意外中罹难。","year":2014},{"title":"2018年:台湾新北市的台北医院凌晨4点在护理之家7楼7A23房编号235的床铺起火，造成9死10重伤6轻伤。","year":2018}]