[{"title":"1812年:1812年战争:哈里森堡垒战役爆发。","year":1812},{"title":"1870年:巴黎民众爆发革命，法国皇帝拿破仑三世被废黜，法兰西第三共和国成立。","year":1870},{"title":"1888年:美国发明家乔治·伊士曼在获得胶卷式照相机的专利后注册了柯达的商标。","year":1888},{"title":"1913年:德国发生华格纳枪击案。","year":1913},{"title":"1939年:二战:日本宣布在欧洲战争中保持中立。","year":1939},{"title":"1944年:二战:英国第十一装甲师解放比利时的安特卫普。","year":1944},{"title":"1948年:荷兰女王威廉明娜宣布因健康原因退位，并由女儿朱丽安娜继位。","year":1948},{"title":"1957年:美国民权运动:小石城事件。","year":1957},{"title":"1958年:中国政府公布关于领海的声明。","year":1958},{"title":"1963年:瑞士航空306号班机空难，机上80人悉数罹难。","year":1963},{"title":"1967年:美国海军陆战队进攻北越的溪生。","year":1967},{"title":"1970年:萨尔瓦多·阿连德当选智利总统。","year":1970},{"title":"1971年:由波音727担任的阿拉斯加航空于阿拉斯加州朱诺附近坠毁，机上111人全部罹难。","year":1971},{"title":"1972年:美国游泳运动员马克·斯皮茨在慕尼黑奥运会上夺得第七枚金牌，成为当时在一届奥运会中获得最多金牌的运动员。此纪录一直维持到2008年，由其同胞且同样擅长游泳的麦可·菲尔普斯于北京奥运独得八枚金牌为止。","year":1972},{"title":"1975年:埃及与以色列签订，埃及收复西奈半岛。","year":1975},{"title":"1990年:朝鲜总理延亨默越过三八线到达汉城，与韩国总理姜英勋举行朝鲜半岛自分裂以来双方的首次总理会谈。","year":1990},{"title":"1995年:拍卖网站ebay（前身为Actionweb）正式成立。","year":1995},{"title":"1995年:于北京开幕，有4750名分别来自181个国家的人士出席。","year":1995},{"title":"1998年:互联网搜索引擎Google成立。","year":1998},{"title":"2001年:东京迪士尼海洋开幕。","year":2001},{"title":"2007年:香港年龄最小的大学生沈诗钧到香港浸会大学上学。","year":2007},{"title":"2010年:新西兰南岛发生了里氏规模7.1级的大地震，造成高达3.5亿新西兰元的经济损失。","year":2010},{"title":"2013年:美国总统奥巴马访问瑞典，强化两国关系、创下美国总统访瑞先例。","year":2013},{"title":"2016年:香港举行第六届立法会选举。当天的地区选举投票率达58.28%，而功能界别选举的投票率则达57.09%。","year":2016}]