[{"title":"1804年:拿破仑战争:西班牙对英国宣战。","year":1804},{"title":"1887年:土耳其向西方国家呼吁，要求调解同俄国的战争。","year":1887},{"title":"1901年:意大利发明家马可尼的研究小组，在加拿大接收到从英国发送出来的第一个横跨大西洋的无线电信号。","year":1901},{"title":"1911年:德里取代加尔各答成为印度的首都。","year":1911},{"title":"1915年:中华民国大总统袁世凯自立为皇帝，改国号为中华帝国。","year":1915},{"title":"1925年:伊朗巴列维王朝建立。","year":1925},{"title":"1936年:中国国民革命军将领张学良、杨虎城在西安扣留了国民政府军事委员会委员长蒋中正以迫使他联共抗日，史称“西安事变”或“双十二事变”。","year":1936},{"title":"1941年 : 第二次世界大战 :罗马尼亚和保加利亚对美国宣战","year":1941},{"title":"1942年:第二次世界大战:纳粹德国军队发起冬季风暴作战试图突破斯大林格勒战役中苏联军队对于轴心国军队所设下的包围网。","year":1942},{"title":"1946年:中华民国派兵进驻西沙和南沙群岛。","year":1946},{"title":"1949年:中华人民共和国根据《开罗宣言》和《波茨坦公告》宣布对南沙群岛的主权。","year":1949},{"title":"1963年:肯尼亚脱离英国统治，宣布独立，乔莫·肯雅塔就任第一任总统。","year":1963},{"title":"1973年:文化大革命:《北京日报》发表了《一个小学生的来信和日记摘抄》，并加长篇编者按语，掀起“破师道尊严”浪潮，是为黄帅事件。","year":1973},{"title":"1979年:全斗焕在韩国发动双十二政变。","year":1979},{"title":"1984年:美国天文学家观测到太阳系外第一颗行星。","year":1984},{"title":"1985年:美国101空降师士兵搭乘的艾罗航空1285号班机在加拿大纽芬兰岛起飞时坠毁，造成248人死亡。","year":1985},{"title":"1989年:香港政府首次执行当然遣返，将51名非自愿返回越南的船民送返。","year":1989},{"title":"1994年:上海地铁一号线开通。","year":1994},{"title":"2004年:索尼电脑娱乐的最新家用便携式游戏机PlayStation Portable问世。","year":2004},{"title":"2006年:日本线上影片分享网站《NICONICO动画（暂定版）》开放测试浏览。","year":2006},{"title":"2009年:香港奥运足球代表队于2009年东亚运动会足球比赛决赛于互射十二码阶段击败日本国家足球队，历史性首次赢得国际性综合体育项目冠军。","year":2009},{"title":"2010年:中国首个极深地下实验室中国锦屏地下实验室投入使用。","year":2010},{"title":"2010年:由包括复旦大学学生在内的18人组成的登山队在黄山迷路，黄山民警张宁海在搜救时殉职，而登山队员获救后态度冷漠，是为复旦黄山门事件或复旦十八驴事件。","year":2010},{"title":"2012年:北朝鲜成功发射光明星3号卫星。","year":2012}]